{"1":{"ID":"52","Nome":"1917","Link":"https:\/\/drive.google.com\/file\/d\/1zgKamW3SwV_lJeKgRO6e7kuOtMHzZm5U\/preview","Genero":"Guerra, Drama, Action, Thriller","Idade":"14","Ano":"2019","Legenda":"0","foto":"15913902265edab0121f658.png","fotogrande":"15913902265edab0121f658.png","banner":null},"2":{"ID":"77","Nome":"A Balada De Buster Scruggs","Link":"https:\/\/drive.google.com\/file\/d\/1dzf_lFgltzEScxo2fVg79khy32TTBTxg\/preview","Genero":"Comedia, Drama, Faroeste","Idade":"16","Ano":"2018","Legenda":"0","foto":"15954777755f190f0f586b1.png","fotogrande":"15954777755f190f0f586b1.png","banner":null},"3":{"ID":"85","Nome":"A Barraca Do Beijo","Link":"https:\/\/drive.google.com\/file\/d\/1kuEYONAtPUzeGdhCrcUz6oVWNp3Cisnh\/preview","Genero":"Romance, Comedia","Idade":"12","Ano":"2018","Legenda":"0","foto":"15967324985f2c345268690.png","fotogrande":"15967324985f2c345268690.png","banner":null},"4":{"ID":"79","Nome":"A Barraca do Beijo 2","Link":"https:\/\/drive.google.com\/file\/d\/1balxHhnnGkt_LY9u8hEP_-7PXczUtyDG\/preview","Genero":"Comedia, Romance","Idade":"12","Ano":"2020","Legenda":"0","foto":"15966431365f2ad740d34ac.png","fotogrande":"15966431365f2ad740d34ac.png","banner":null},"5":{"ID":"109","Nome":"A Bela e a Fera","Link":"https:\/\/drive.google.com\/file\/d\/1F40Z_fQzbpD-RXgfSNc9lczPiJ9jKEXQ\/preview","Genero":"Musical, Romance","Idade":"10","Ano":"2017","Legenda":"0","foto":"16033778405f919ab022af5.png","fotogrande":"16033778405f919ab022af5.png","banner":null},"6":{"ID":"110","Nome":"A Bela e a Fera","Link":"https:\/\/drive.google.com\/file\/d\/1Or0NZntalumoSlrMiY2KxGtCWM3BOXLc\/preview","Genero":"Fantasia, Romance","Idade":"10","Ano":"2014","Legenda":"0","foto":"16034712065f9307668ca2c.png","fotogrande":"16034712065f9307668ca2c.png","banner":null},"7":{"ID":"151","Nome":"A Caminho da Lua","Link":"https:\/\/drive.google.com\/file\/d\/1bCxo1Q81FzF37j7IQJyqLSrDvHLTTS8M\/preview","Genero":"Animacao, Musical, Familia","Idade":"10","Ano":"2020","Legenda":"1","foto":"1610645683600080b3aa471.png","fotogrande":"1610645683600080b3b004d.png","banner":"1610645683600080b3a30d1.png"},"8":{"ID":"123","Nome":"A Cor Purpura","Link":"https:\/\/drive.google.com\/file\/d\/1CNVl5iJ6ErizmtJ-6NFDHnU29I7eTVyX\/preview","Genero":"Drama, Obra de Epoca","Idade":"14","Ano":"1985","Legenda":"0","foto":"16067397995fc4e757c0c36.png","fotogrande":"16067397995fc4e757c0c36.png","banner":null},"9":{"ID":"168","Nome":"A Dama De Vermelho","Link":"https:\/\/drive.google.com\/file\/d\/1W94EIRq1Q26vPJSMeOGcbklSfTzQwMMr\/preview","Genero":"Comedia, Romance","Idade":"12","Ano":"1984","Legenda":"0","foto":"1613521709602c632dcb168.png","fotogrande":"1613521709602c632da3390.png","banner":"1613521709602c632d7b0ff.png"},"10":{"ID":"89","Nome":"A Dama e o Vagabundo","Link":"https:\/\/drive.google.com\/file\/d\/1K0DyqOdjBhZVnI5ZiOXvEbOFKiniGxgD\/preview","Genero":"Romance, Comedia, Familia","Idade":"Livre","Ano":"2019","Legenda":"0","foto":"15970184965f309180c37ea.png","fotogrande":"15970184965f309180c37ea.png","banner":null},"11":{"ID":"18","Nome":"A Era Do Gelo","Link":"https:\/\/drive.google.com\/file\/d\/11y0Gn_PW8A3IjD_L1BujibVrHJKZYyYA\/preview","Genero":"Animacao, Comedia, Familia, Aventura","Idade":"Livre","Ano":"2002","Legenda":"1","foto":"15874293295e9e3fd175aac.png","fotogrande":"15874293295e9e3fd175aac.png","banner":null},"12":{"ID":"39","Nome":"A Extraordinaria Jornada Do Fakir","Link":"https:\/\/drive.google.com\/file\/d\/1nJxcW1zLzHt7Z7RqpRj0hni3ArZy8drI\/preview","Genero":"Comedia, Aventura, Drama","Idade":"12","Ano":"2018","Legenda":"0","foto":"15907805305ed162721873e.png","fotogrande":"15907805305ed162721873e.png","banner":null},"13":{"ID":"45","Nome":"A Hora Da Sua Morte","Link":"https:\/\/drive.google.com\/file\/d\/1Cjlsr_MiAUruJZBAhaMJyoqFZU9DEVuV\/preview","Genero":"Terror, Thriller","Idade":"14","Ano":"2019","Legenda":"0","foto":"15908080755ed1ce0be3860.png","fotogrande":"15908080755ed1ce0be3860.png","banner":null},"14":{"ID":"124","Nome":"A Lista de Schindler","Link":"https:\/\/drive.google.com\/file\/d\/1V8uHO6U8G1whjcetOc7n7DIByNPR46Wk\/preview","Genero":"Guerra, Drama","Idade":"14","Ano":"1993","Legenda":"0","foto":"16067401175fc4e8951daaa.png","fotogrande":"16067401175fc4e8951daaa.png","banner":null},"15":{"ID":"46","Nome":"A Maldi\u00e7ao De Sharon Tate","Link":"https:\/\/drive.google.com\/file\/d\/1Lrt5VikKN1e8Kh_jJJS3-e2NLNr7XX5l\/preview","Genero":"Terror, Thriller","Idade":"16","Ano":"2019","Legenda":"0","foto":"15908142015ed1e5f9d4fbe.png","fotogrande":"15908142015ed1e5f9d4fbe.png","banner":null},"16":{"ID":"24","Nome":"A Noiva Cadaver","Link":"https:\/\/drive.google.com\/file\/d\/1LteAZHZLNMprTcgNGCkQP10QLPT77xfR\/preview","Genero":"Romance, Fantasia, Animacao","Idade":"Livre","Ano":"2005","Legenda":"1","foto":"15882996315eab876fb84be.png","fotogrande":"15882996315eab876fb84be.png","banner":null},"17":{"ID":"47","Nome":"A Princesa e a Plebeia","Link":"https:\/\/drive.google.com\/file\/d\/1dnb4FZX5P_3LlUrXRONQv3pq19lNWh3Z\/preview","Genero":"Romance","Idade":"Livre","Ano":"2018","Legenda":"0","foto":"15908144905ed1e71aa4083.png","fotogrande":"15908144905ed1e71aa4083.png","banner":null},"18":{"ID":"126","Nome":"A Princesa e a Plebeia - Nova Aventura","Link":"https:\/\/drive.google.com\/file\/d\/1xdr6YdCu3GkKvIKslBt5btkJoQqFqN5B\/preview","Genero":"Comedia, Romance","Idade":"Livre","Ano":"2020","Legenda":"0","foto":"16067411565fc4eca4ddd82.png","fotogrande":"16067411565fc4eca4ddd82.png","banner":null},"19":{"ID":"16","Nome":"A Procura Da Felicidade","Link":"https:\/\/drive.google.com\/file\/d\/1yNrZpdfyZEFTgE_21txlWJAQFn4x9WAh\/preview","Genero":"Drama, Gospel","Idade":"Livre","Ano":"2006","Legenda":"1","foto":"15874234155e9e28b7424b0.png","fotogrande":"15874234155e9e28b7424b0.png","banner":null},"20":{"ID":"125","Nome":"A Vida E Bela","Link":"https:\/\/drive.google.com\/file\/d\/18v5CipUADmGP12cdplWkgPiGi_y-wvLF\/preview","Genero":"Guerra, Romance","Idade":"Livre","Ano":"1997","Legenda":"0","foto":"16067406565fc4eab0c86aa.png","fotogrande":"16067406565fc4eab0c86aa.png","banner":null},"21":{"ID":"40","Nome":"A Vingan\u00e7a De Lefty Brown","Link":"https:\/\/drive.google.com\/file\/d\/1KWnVr6nuAPr4pYF9ZfcUkJPR3PPE31ro\/preview","Genero":"Faroeste","Idade":"16","Ano":"2017","Legenda":"0","foto":"15907807275ed1633746e49.png","fotogrande":"15907807275ed1633746e49.png","banner":null},"22":{"ID":"1","Nome":"Abigail e a Cidade Proibida","Link":"https:\/\/drive.google.com\/file\/d\/1t5GhXrBUiychj08D4Wk5afFI8bFaoqRI\/preview","Genero":"Aventura, Fantasia","Idade":"12","Ano":"2020","Legenda":"1","foto":"16075302565fd0f710b5748.png","fotogrande":"16075302565fd0f710b5b30.png","banner":null},"23":{"ID":"2","Nome":"Abominavel","Link":"https:\/\/drive.google.com\/file\/d\/1qvFnLZHN4khFM9bpzGsRG6_8CPvp3ZDb\/preview","Genero":"Animacao, Aventura, Comedia","Idade":"Livre","Ano":"2019","Legenda":"1","foto":"15869065315e9645a384113.png","fotogrande":"15869065315e9645a384113.png","banner":null},"24":{"ID":"195","Nome":"Ace Ventura - Um Detetive Diferente","Link":"https:\/\/drive.google.com\/file\/d\/1yPvvZFj8inEM2R2QlxkMOeJ41tEZwvBQ\/preview","Genero":"Comedia, Aventura","Idade":"Livre","Ano":"1994","Legenda":"1","foto":"1616536828605a64fc60ac8.png","fotogrande":"1616536828605a64fc54caf.png","banner":"1616536828605a64fc47f61.png"},"25":{"ID":"196","Nome":"Ace Ventura 2 - Um Maluco na Africa","Link":"https:\/\/drive.google.com\/file\/d\/1OH9vIpj868AXQc49zT4mHgtA-2CVA3r5\/preview","Genero":"Comedia, Aventura, Misterio","Idade":"Livre","Ano":"1995","Legenda":"1","foto":"1616537111605a66174a940.png","fotogrande":"1616537111605a66173e8be.png","banner":"1616537111605a6617324ca.png"},"26":{"ID":"152","Nome":"After","Link":"https:\/\/drive.google.com\/file\/d\/1HQdHcmVF_tRdpH-PxqTpaEdmV41TL80y\/preview","Genero":"Romance, Drama","Idade":"14","Ano":"2019","Legenda":"0","foto":"16109226556004ba9f34a54.png","fotogrande":"16109226556004ba9f2b96c.png","banner":"16109226556004ba9f1fcd9.png"},"27":{"ID":"210","Nome":"Al\u00e9m da Vida","Link":"https:\/\/drive.google.com\/file\/d\/1jCmhd4mXwpLkgfvcVcsIqCencSjVpP3M\/preview","Genero":"Drama, Catastrofe","Idade":"12","Ano":"2010","Legenda":"1","foto":"162879755561157a7379744.png","fotogrande":"162879755561157a7374a20.png","banner":"162879755561157a7369f48.png"},"28":{"ID":"174","Nome":"Amor\u00b2","Link":"https:\/\/drive.google.com\/file\/d\/1QMCeIN6_6_XLfwb-GvgJRk4N-_VHwMWA\/preview","Genero":"Comedia, Romance","Idade":"12","Ano":"2021","Legenda":"0","foto":"161403679860343f3e7f185.png","fotogrande":"161403679860343f3e75d3c.png","banner":"161403679860343f3e6a4a3.png"},"29":{"ID":"80","Nome":"Aquaman","Link":"https:\/\/drive.google.com\/file\/d\/1Yvs5SzOVlD1IBFE8WzU1LNcPx5OaTnAl\/preview","Genero":"Action, Aventura, Fantasia","Idade":"12","Ano":"2018","Legenda":"0","foto":"15966436495f2ad941883e1.png","fotogrande":"15966436495f2ad941883e1.png","banner":null},"30":{"ID":"119","Nome":"Artemis Fowl - O Mundo Secreto","Link":"https:\/\/drive.google.com\/file\/d\/18hedC7oPu2Lj3T4ZOROfx_NkpGIXCacq\/preview","Genero":"Aventura, Fantasia, Ficcao Cientifica, Familia, Action","Idade":"10","Ano":"2020","Legenda":"0","foto":"16054717515fb18e0799955.png","fotogrande":"16054717515fb18e0799955.png","banner":null},"31":{"ID":"127","Nome":"As Aventuras de Pi","Link":"https:\/\/drive.google.com\/file\/d\/1lkZTjah4GAu2MEnhpgHhlEj9_r4pIoGg\/preview","Genero":"Aventura, Drama","Idade":"10","Ano":"2012","Legenda":"0","foto":"16067414965fc4edf8696f3.png","fotogrande":"16067414965fc4edf8696f3.png","banner":null},"32":{"ID":"99","Nome":"As Branquelas","Link":"https:\/\/drive.google.com\/file\/d\/1pEl91IPe22gUs-LRVjvy3HcBsYGWBxKs\/preview","Genero":"Comedia","Idade":"12","Ano":"2004","Legenda":"1","foto":"16013074615f720345cf76c.png","fotogrande":"16013074615f720345cf76c.png","banner":null},"33":{"ID":"128","Nome":"Ate o Ultimo Homem","Link":"https:\/\/drive.google.com\/file\/d\/1mlNBZdG9Q6bZ43QUz1JzwdkM2zUftaSM\/preview","Genero":"Guerra, Drama, Gospel","Idade":"16","Ano":"2016","Legenda":"0","foto":"16067419045fc4ef90c65c8.png","fotogrande":"16067419045fc4ef90c65c8.png","banner":null},"34":{"ID":"48","Nome":"Aves de Rapina - Arlequina e sua Emancipacao Fantabulosa","Link":"https:\/\/drive.google.com\/file\/d\/1xI_bDRp6K_zciE6ep_qFUT92x-2sVdwK\/preview","Genero":"Action, Crime, Comedia","Idade":"16","Ano":"2020","Legenda":"0","foto":"15908147835ed1e83fb5d32.png","fotogrande":"15908147835ed1e83fb5d32.png","banner":null},"35":{"ID":"10","Nome":"Bad Boys Para Sempre","Link":"https:\/\/drive.google.com\/file\/d\/1SbG7L8V5qEsnI9UpYrdjwd4a_850ew0x\/preview","Genero":"Thriller, Action, Crime","Idade":"16","Ano":"2020","Legenda":"1","foto":"15869072095e964849101b1.png","fotogrande":"15869072095e964849101b1.png","banner":null},"36":{"ID":"120","Nome":"Ben 10 - Contra o Universo","Link":"https:\/\/drive.google.com\/file\/d\/1c9uH9FRmkcyVQnLMUmtk9-qoo72ccchw\/preview","Genero":"Animacao, Action, Aventura, Ficcao cientifica, Cinema TV","Idade":"Livre","Ano":"2020","Legenda":"0","foto":"16054722245fb18fe0d30b6.png","fotogrande":"16054722245fb18fe0d30b6.png","banner":null},"37":{"ID":"175","Nome":"Bill e Ted - Encare a Musica","Link":"https:\/\/drive.google.com\/file\/d\/1npPsvlI5PBJq9Zis9uuaJGKVJtSWfB5O\/preview","Genero":"Comedia, Ficcao cientifica","Idade":"10","Ano":"2020","Legenda":"0","foto":"1614037270603441163619d.png","fotogrande":"1614037270603441162b915.png","banner":"1614037270603441162184d.png"},"38":{"ID":"14","Nome":"Bloodshot","Link":"https:\/\/drive.google.com\/file\/d\/1g7YqztKFoKUgvyrnf4uJLAgYuO89on-c\/preview","Genero":"Action, Ficcao cientifica","Idade":"14","Ano":"2020","Legenda":"1","foto":"15874163655e9e0d2da8060.png","fotogrande":"15874163655e9e0d2da8060.png","banner":null},"39":{"ID":"118","Nome":"Bob Esponja - O Incrivel Resgate","Link":"https:\/\/drive.google.com\/file\/d\/1ImjBtOPvhWqcN5HvAPaNmrU1HqTAUrVR\/preview","Genero":"Fantasia, Animacao, Aventura, Comedia, Familia","Idade":"Livre","Ano":"2020","Legenda":"0","foto":"16051992505fad65921bd2d.png","fotogrande":"16051992505fad65921bd2d.png","banner":null},"40":{"ID":"207","Nome":"Brinquedo Assassino","Link":"https:\/\/drive.google.com\/file\/d\/1uQ7R3UOCfgA978OIhWoOAn0eXT70kIGu\/preview","Genero":"Terror, Misterio ","Idade":"16","Ano":"1988","Legenda":"0","foto":"1617731727606ca08f10025.png","fotogrande":"1617731727606ca08f07f08.png","banner":"1617731726606ca08ef3d93.png"},"41":{"ID":"121","Nome":"Buffalo Boys","Link":"https:\/\/drive.google.com\/file\/d\/13UjykoJVvADucm0kxzx-17vqdRRwP3d1\/preview","Genero":"Drama, Action","Idade":"16","Ano":"2018","Legenda":"0","foto":"16054725575fb1912d60e4e.png","fotogrande":"16054725575fb1912d60e4e.png","banner":null},"42":{"ID":"53","Nome":"Bumblebee","Link":"https:\/\/drive.google.com\/file\/d\/12oF7e5qOmeD7iKjFOlzAPwA_BwSUJ28P\/preview","Genero":"Action, Aventura, Ficcao cientifica","Idade":"12","Ano":"2018","Legenda":"0","foto":"15913905285edab14029259.png","fotogrande":"15913905285edab14029259.png","banner":null},"43":{"ID":"206","Nome":"Cabras da Peste","Link":"https:\/\/drive.google.com\/file\/d\/1acDj8h5w61OwxWjCDIk25CYjN-33QHnq\/preview","Genero":"Crime, Aventura, Comedia","Idade":"16","Ano":"2021","Legenda":"0","foto":"1617731418606c9f5a943e1.png","fotogrande":"1617731415606c9f576cdd0.png","banner":"1617731414606c9f56e38f6.png"},"44":{"ID":"211","Nome":"Ca\u00e7adores de Drag\u00f5es","Link":"https:\/\/drive.google.com\/file\/d\/1s-SbNtChVJ6GBZPHfCfJYpM0XC_zrJd3\/preview","Genero":"Fantasia","Idade":"10","Ano":"2008","Legenda":"0","foto":"162879794661157bfa6484c.png","fotogrande":"162879794661157bfa470c6.png","banner":"162879794661157bfa295a0.png"},"45":{"ID":"11","Nome":"Caminhos De Sangue","Link":"https:\/\/drive.google.com\/file\/d\/1PIB94gypPfBuq2Wn2rHgXajKuemcfWg9\/preview","Genero":"Thriller, Crime","Idade":"16","Ano":"2019","Legenda":"1","foto":"15869072895e9648996e66a.png","fotogrande":"15869072895e9648996e66a.png","banner":null},"46":{"ID":"49","Nome":"Campo do Medo","Link":"https:\/\/drive.google.com\/file\/d\/1T9VWVaZop5Ms5RtKCTSVAdcn4tqqXisQ\/preview","Genero":"Terror, Drama, Thriller","Idade":"16","Ano":"2019","Legenda":"0","foto":"15908149035ed1e8b793653.png","fotogrande":"15908149035ed1e8b793653.png","banner":null},"47":{"ID":"28","Nome":"Cartas para Deus","Link":"https:\/\/drive.google.com\/file\/d\/1KxymOdknGrtO0lj1Xw1S0-_uWTjFA5Md\/preview","Genero":"Drama, Gospel","Idade":"Livre","Ano":"2011","Legenda":"1","foto":"15883826065eaccb8e84866.png","fotogrande":"15883826065eaccb8e84866.png","banner":null},"48":{"ID":"221","Nome":"Casa Comigo","Link":"https:\/\/drive.google.com\/file\/d\/1dZegxqyLK_ITx4GpTcWhptuHPsTfP3zH\/preview","Genero":"Comedia, Romance","Idade":"12","Ano":"2010","Legenda":"0","foto":"16310518906137e0727e02f.png","fotogrande":"16310518896137e071ce8ae.png","banner":"16310518896137e071281c3.png"},"49":{"ID":"108","Nome":"Cinderela","Link":"https:\/\/drive.google.com\/file\/d\/1DwR0_YnD2h8Th9aRXBtvoNL_p18xctip\/preview","Genero":"Romance, Fantasia","Idade":"Livre","Ano":"2015","Legenda":"1","foto":"16033341105f90efded2354.png","fotogrande":"16033341105f90efded2354.png","banner":null},"50":{"ID":"50","Nome":"Code 8 - Renegados","Link":"https:\/\/drive.google.com\/file\/d\/1wUG8hf84OO8OQO-EemoHw1COyqUy4m4L\/preview","Genero":"Ficcao cientifica, Action, Crime, Thriller, Drama","Idade":"14","Ano":"2019","Legenda":"0","foto":"15908151145ed1e98aa9198.png","fotogrande":"15908151145ed1e98aa9198.png","banner":null},"51":{"ID":"164","Nome":"Conven\u00e7\u00e3o das Bruxas","Link":"https:\/\/drive.google.com\/file\/d\/12pAwA8LpUNNZufoOqtbIKNMny0drWmG_\/preview","Genero":"Fantasia, Familia, Aventura, Comedia, Terror","Idade":"10","Ano":"2020","Legenda":"0","foto":"1612976889602412f9eacbb.png","fotogrande":"1612976889602412f9caeff.png","banner":"1612976889602412f9a8f8e.png"},"52":{"ID":"42","Nome":"Coraline e o Mundo Secreto","Link":"https:\/\/drive.google.com\/file\/d\/15Nrw-FpRvXX_3F7bif52Lp1kZZx-NZQT\/preview","Genero":"Animacao, Familia","Idade":"10","Ano":"2019","Legenda":"0","foto":"15908073685ed1cb4875c95.png","fotogrande":"15908073685ed1cb4875c95.png","banner":null},"53":{"ID":"149","Nome":"Corgi - Top Dog","Link":"https:\/\/drive.google.com\/file\/d\/1UbOLSI1mfYyTTDHqAkADxLZ2mYlVMpN_\/preview","Genero":"Animacao, Familia, Comedia","Idade":"Livre","Ano":"2019","Legenda":"0","foto":"16105039325ffe56fc97d15.png","fotogrande":"16105039325ffe56fcb1306.png","banner":"16105039325ffe56fc7a379.png"},"54":{"ID":"3","Nome":"Coringa","Link":"https:\/\/drive.google.com\/file\/d\/1qtNhJNniIU54GUhHa7YVoGw21DbtDNOC\/preview","Genero":"Drama, Crime, Thriller","Idade":"17","Ano":"2019","Legenda":"1","foto":"15869065935e9645e14cfc4.png","fotogrande":"15869065935e9645e14cfc4.png","banner":null},"55":{"ID":"75","Nome":"Crepusculo","Link":"https:\/\/drive.google.com\/file\/d\/1P9CflfbDS_Sgnkjfph9jIdWkLmlrZ10D\/preview","Genero":"Fantasia, Drama, Romance","Idade":"12","Ano":"2008","Legenda":"0","foto":"15954764065f1909b676512.png","fotogrande":"15954764065f1909b676512.png","banner":null},"56":{"ID":"88","Nome":"Crepusculo - Eclipse","Link":"https:\/\/drive.google.com\/file\/d\/16s9bkC1MBWILEff4HqRIwN9LXOf1R4Ia\/preview","Genero":"Aventura, Fantasia, Drama, Romance","Idade":"14","Ano":"2010","Legenda":"0","foto":"15967333715f2c37bb1fac6.png","fotogrande":"15967333715f2c37bb1fac6.png","banner":null},"57":{"ID":"87","Nome":"Crepusculo - Lua Nova","Link":"https:\/\/drive.google.com\/file\/d\/1aKNEVJs-Q3mqi2rC0Gza2O2txphBoXM7\/preview","Genero":"Aventura, Fantasia, Drama, Romance","Idade":"12","Ano":"2009","Legenda":"0","foto":"15967331755f2c36f72d811.png","fotogrande":"15967331755f2c36f72d811.png","banner":null},"58":{"ID":"91","Nome":"Crepusculo: Amanhecer - Parte 1","Link":"https:\/\/drive.google.com\/file\/d\/1Tm7TyZN4NVXiAANH5bbg2VcXbSYkeDMo\/preview","Genero":"Aventura, Fantasia, Romance","Idade":"14","Ano":"2011","Legenda":"0","foto":"15970301415f30befd43b7a.png","fotogrande":"15970301415f30befd43b7a.png","banner":null},"59":{"ID":"92","Nome":"Crepusculo: Amanhecer - Parte 2","Link":"https:\/\/drive.google.com\/file\/d\/1tX5OULCH9uXdr-UpGvQqeHknpggak8Qh\/preview","Genero":"Aventura, Fantasia, Drama, Romance","Idade":"12","Ano":"2012","Legenda":"0","foto":"15970303565f30bfd4095db.png","fotogrande":"15970303565f30bfd4095db.png","banner":null},"60":{"ID":"212","Nome":"Cruella","Link":"https:\/\/drive.google.com\/file\/d\/1FWclXCOaG8nXyme1TN1Xe0IgtPMmxLwg\/preview","Genero":"Comedia, Crime","Idade":"12","Ano":"2021","Legenda":"0","foto":"162879857261157e6c4269b.png","fotogrande":"162879857261157e6c3c316.png","banner":"162879857261157e6c0abc5.png"},"61":{"ID":"184","Nome":"DeadPool","Link":"https:\/\/drive.google.com\/file\/d\/1jwOXscGEtdGqke_pGVEIKdkZdp9zx6o8\/preview","Genero":"Action, Fantasia","Idade":"16","Ano":"2016","Legenda":"0","foto":"1614695099603e4abb54a25.png","fotogrande":"1614695099603e4abb4e45c.png","banner":"1614695099603e4abb40adf.png"},"62":{"ID":"37","Nome":"Divertida Mente","Link":"https:\/\/drive.google.com\/file\/d\/1pv4ScDZgIHdd_pQjp-iZ4YaL1dHuj4nG\/preview","Genero":"Drama, Comedia, Animacao, Familia","Idade":"Livre","Ano":"2015","Legenda":"0","foto":"15907801015ed160c57a2c8.png","fotogrande":"15907801015ed160c57a2c8.png","banner":null},"63":{"ID":"176","Nome":"Doutor Estranho","Link":"https:\/\/drive.google.com\/file\/d\/1DuvtHLSMsL3YLtNPZDULyiu-xqsuIwC6\/preview","Genero":"Action, Fantasia","Idade":"12","Ano":"2016","Legenda":"0","foto":"16140376146034426eb0df5.png","fotogrande":"16140376146034426ea6dd6.png","banner":"16140376146034426e9d90a.png"},"64":{"ID":"98","Nome":"Dragon Ball: Em Busca Do Poder","Link":"https:\/\/drive.google.com\/file\/d\/1fZyQtQDDntVdTzhuEhZJRjlQhIhvJim4\/preview","Genero":"Action, Animacao, Comedia","Idade":"12","Ano":"1996","Legenda":"0","foto":"16012605325f714bf4223cb.png","fotogrande":"16012605325f714bf4223cb.png","banner":null},"65":{"ID":"222","Nome":"Edward M\u00e3os de Tesoura","Link":"https:\/\/drive.google.com\/file\/d\/1HWjknt4sVp8UHpCiaC2lrN1k9bsFgcPO\/preview","Genero":"Fantasia, Romance","Idade":"Livre","Ano":"1990","Legenda":"0","foto":"16310528666137e442b1c15.png","fotogrande":"16310528666137e442a3797.png","banner":"16310528666137e44294bcc.png"},"66":{"ID":"97","Nome":"Enola Holmes","Link":"https:\/\/drive.google.com\/file\/d\/1CCfadJsSv36luazR6V4DgpEls8eASSn8\/preview","Genero":"Aventura, Crime, Drama, Misterio","Idade":"11","Ano":"2020","Legenda":"0","foto":"16012603355f714b2fe71e7.png","fotogrande":"16012603355f714b2fe71e7.png","banner":null},"67":{"ID":"84","Nome":"Enrolados","Link":"https:\/\/drive.google.com\/file\/d\/1KyVimdAaEuc5rHBElgCyMeFOiHboHguo\/preview","Genero":"Animacao, Infantil","Idade":"Livre","Ano":"2010","Legenda":"0","foto":"15966647085f2b2b84f2399.png","fotogrande":"15966647085f2b2b84f2399.png","banner":null},"68":{"ID":"58","Nome":"Espada da Vinganca - Ate a Ultima Linha","Link":"https:\/\/drive.google.com\/file\/d\/1DOwkiXt6Hhi69YGNFm2-Hmh5JrXUBbz1\/preview","Genero":"Action, Fantasia","Idade":"12","Ano":"2020","Legenda":"0","foto":"15922764235ee835c72b584.png","fotogrande":"15922764235ee835c72b584.png","banner":null},"69":{"ID":"177","Nome":"Flora e Ulysses","Link":"https:\/\/drive.google.com\/file\/d\/1tjdQWpDujraHtTrRmvyxwf4pBs4FCAvV\/preview","Genero":"Aventura, Familia, Comedia","Idade":"10","Ano":"2021","Legenda":"0","foto":"16140383506034454e910cc.png","fotogrande":"16140383506034454e88e16.png","banner":"16140383506034454e8051a.png"},"70":{"ID":"55","Nome":"Forrest Gump - O Contador De Historias","Link":"https:\/\/drive.google.com\/file\/d\/1r2hbpYTJeEKA1V2kJcXDdzPGAuwXjHcH\/preview","Genero":"Comedia, Drama, Romance","Idade":"14","Ano":"1994","Legenda":"0","foto":"15921693675ee693974a2e4.png","fotogrande":"15921693675ee693974a2e4.png","banner":null},"71":{"ID":"21","Nome":"Frozen 2","Link":"https:\/\/drive.google.com\/file\/d\/1kjFjQGsFVJIvUgbhu7nA5k-ojdTyTsQm\/preview","Genero":"Animacao, Familia, Aventura","Idade":"Livre","Ano":"2019","Legenda":"1","foto":"15877830435ea3a58310964.png","fotogrande":"15877830435ea3a58310964.png","banner":null},"72":{"ID":"76","Nome":"Gente Grande","Link":"https:\/\/drive.google.com\/file\/d\/1_Rc_onAzM44OyqIS5CU1CY8EvKuqlHk5\/preview","Genero":"Comedia","Idade":"12","Ano":"2010","Legenda":"0","foto":"15954766375f190a9d2a28f.png","fotogrande":"15954766375f190a9d2a28f.png","banner":null},"73":{"ID":"38","Nome":"Gente Grande 2","Link":"https:\/\/drive.google.com\/file\/d\/1sstQI9JcaRjqV9VhEmwhnsGmprOjrkJo\/preview","Genero":"Comedia","Idade":"12","Ano":"2013","Legenda":"0","foto":"15907803215ed161a19e239.png","fotogrande":"15907803215ed161a19e239.png","banner":null},"74":{"ID":"213","Nome":"Godzilla vs Kong","Link":"https:\/\/drive.google.com\/file\/d\/1ijYSo8tpICVHqUfyeHXcd2zv1jY8MblR\/preview","Genero":"Ficcao Cientifica, Action","Idade":"14","Ano":"2021","Legenda":"0","foto":"16287991156115808b6ff12.png","fotogrande":"16287991156115808b6881c.png","banner":"16287991156115808b60a0a.png"},"75":{"ID":"163","Nome":"Hancock","Link":"https:\/\/drive.google.com\/file\/d\/137RI9_2_YbWZXvvXlhDsny8ZreASN612\/preview","Genero":"Action, Fantasia","Idade":"12","Ano":"2008","Legenda":"0","foto":"1612478097601c7691cc52b.png","fotogrande":"1612478097601c7691c196a.png","banner":"1612478097601c7691b8f76.png"},"76":{"ID":"61","Nome":"Harry Potter E A Ordem Da Fenix","Link":"https:\/\/drive.google.com\/file\/d\/1I2IJLdThdMzGG5alCKQwTW_yhi9WRXhg\/preview","Genero":"Aventura, Fantasia, Misterio","Idade":"Livre","Ano":"2007","Legenda":"0","foto":"15924511925eeae0788f8eb.png","fotogrande":"15924511925eeae0788f8eb.png","banner":null},"77":{"ID":"129","Nome":"Historia de um Casamento","Link":"https:\/\/drive.google.com\/file\/d\/1dXQzw11vckaqr99eEgTZHei5jb6nlkxp\/preview","Genero":"Romance, Drama","Idade":"14","Ano":"2019","Legenda":"0","foto":"16067428385fc4f3367b97e.png","fotogrande":"16067428385fc4f3367b97e.png","banner":null},"78":{"ID":"173","Nome":"Historias Cruzadas","Link":"https:\/\/drive.google.com\/file\/d\/1S7mzUR7iVKCNchU_vSYkLG0aqLFr7PFO\/preview","Genero":"Drama, Romance","Idade":"12","Ano":"2011","Legenda":"0","foto":"1613599698602d93d298ed6.png","fotogrande":"1613599698602d93d2768ec.png","banner":"1613599698602d93d253a63.png"},"79":{"ID":"205","Nome":"Homem-Aranha","Link":"https:\/\/drive.google.com\/file\/d\/16_a91d42VK2Alp0d22v-xGSZ4dcoaI-u\/preview","Genero":"Action, Fantasia, Aventura, Drama, \u200eFiccao Cientifica","Idade":"Livre","Ano":"2002","Legenda":"0","foto":"1617730844606c9d1ccd65f.png","fotogrande":"1617730844606c9d1cc61d9.png","banner":"1617730844606c9d1cbddd0.png"},"80":{"ID":"62","Nome":"Homem-Aranha No Aranhaverso","Link":"https:\/\/drive.google.com\/file\/d\/1hR3EbIwzEfy-39LRY_O2WPya4h4tnx4f\/preview","Genero":"Action, Aventura, Animacao, Ficcao cientifica, Comedia","Idade":"12","Ano":"2018","Legenda":"0","foto":"15925180585eebe5aaf08df.png","fotogrande":"15925180585eebe5aaf08df.png","banner":null},"81":{"ID":"103","Nome":"It - Capitulo Dois","Link":"https:\/\/drive.google.com\/file\/d\/1RL7mxn3WkyxP-Mu9L59WTxEa6qzDIIq1\/preview","Genero":"Terror, Thriller","Idade":"16","Ano":"2019","Legenda":"0","foto":"16030588705f8cbcb6cb5d3.png","fotogrande":"16030588705f8cbcb6cb5d3.png","banner":null},"82":{"ID":"166","Nome":"Jiu Jitsu","Link":"https:\/\/drive.google.com\/file\/d\/1qyTuGt6BpR0vBeXvQ-Gb6cmbM2mCdDta\/preview","Genero":"Fantasia, Action, Ficcao cientifica","Idade":"16","Ano":"2020","Legenda":"0","foto":"16129779326024170c82c6f.png","fotogrande":"16129779326024170c76ccd.png","banner":"16129779326024170c6b2a2.png"},"83":{"ID":"30","Nome":"Jogador N1","Link":"https:\/\/drive.google.com\/file\/d\/1rswoQwWi0BVWpRPAmKIecDNitZ9efeSN\/preview","Genero":"Aventura, Ficcao cientifica","Idade":"12","Ano":"2018","Legenda":"1","foto":"15889049005eb4c3c422767.png","fotogrande":"15889049005eb4c3c422767.png","banner":null},"84":{"ID":"156","Nome":"Jogos Mortais","Link":"https:\/\/drive.google.com\/file\/d\/1bBysa-6RjLWAiyCqWq1JqCOsESIuwIbR\/preview","Genero":"Terror, Thriller, Crime, Misterio","Idade":"18","Ano":"2004","Legenda":"0","foto":"1612475050601c6aaa3ff9a.png","fotogrande":"1612475050601c6aaa27770.png","banner":"1612475050601c6aaa0ba00.png"},"85":{"ID":"162","Nome":"Jogos Mortais - Jigsaw","Link":"https:\/\/drive.google.com\/file\/d\/1mtNZG7auF4pbmig6dmoYZwLJh_V4RHKJ\/preview","Genero":"Terror, Thriller, Crime, Mist\u00e9rio","Idade":"18","Ano":"2017","Legenda":"0","foto":"1612477670601c74e655397.png","fotogrande":"1612477670601c74e64b926.png","banner":"1612477670601c74e640c11.png"},"86":{"ID":"157","Nome":"Jogos Mortais 2","Link":"https:\/\/drive.google.com\/file\/d\/1OHDDQ7vRozuuJZoQIIWy39-XOysXplpj\/preview","Genero":"Terror, Thriller, Crime, Misterio","Idade":"16","Ano":"2005","Legenda":"0","foto":"1612475456601c6c40a6c2c.png","fotogrande":"1612475456601c6c409f66f.png","banner":"1612475456601c6c409705c.png"},"87":{"ID":"158","Nome":"Jogos Mortais 3","Link":"https:\/\/drive.google.com\/file\/d\/1KjVgpBUbsyFUFvCSYCOriB4IUg21ljwD\/preview","Genero":"Terror, Thriller, Crime, Misterio","Idade":"18","Ano":"2006","Legenda":"0","foto":"1612475828601c6db4ba7ce.png","fotogrande":"1612475828601c6db4b2579.png","banner":"1612475828601c6db4a99b8.png"},"88":{"ID":"159","Nome":"Jogos Mortais 4","Link":"https:\/\/drive.google.com\/file\/d\/1J32g4Nqqgqb6aeCfS2SGgrX2wwtqjwv8\/preview","Genero":"Terror, Thriller, Crime, Misterio","Idade":"18","Ano":"2007","Legenda":"0","foto":"1612476666601c70fa187f8.png","fotogrande":"1612476666601c70fa1061a.png","banner":"1612476666601c70fa06270.png"},"89":{"ID":"160","Nome":"Jogos Mortais 5","Link":"https:\/\/drive.google.com\/file\/d\/176aaQUZa2WQqy_jYtwJcIKEo2nYPBDFd\/preview","Genero":"Terror, Thriller, Crime, Misterio","Idade":"18","Ano":"2008","Legenda":"0","foto":"1612476977601c72310d803.png","fotogrande":"1612476976601c7230df3ff.png","banner":"1612476976601c7230c0bfa.png"},"90":{"ID":"161","Nome":"Jogos Mortais 6","Link":"https:\/\/drive.google.com\/file\/d\/1HrPPK_Yt1oIMY2qk0gkG_TTlXPDhyDd1\/preview","Genero":"Terror, Thriller, Crime, Misterio","Idade":"16","Ano":"2009","Legenda":"0","foto":"1612477294601c736eb47ea.png","fotogrande":"1612477294601c736eaba44.png","banner":"1612477294601c736ea2438.png"},"91":{"ID":"111","Nome":"Jogos Vorazes","Link":"https:\/\/drive.google.com\/file\/d\/1PHaZQqwPmlADlLeAX0Y15aOpxCKUd5XJ\/preview","Genero":"Action, Ficcao cientifica","Idade":"12","Ano":"2012","Legenda":"0","foto":"16037669705f978abaeaf24.png","fotogrande":"16037669705f978abaeaf24.png","banner":null},"92":{"ID":"199","Nome":"Jogos Vorazes -  A Esperan\u00e7a parte 1","Link":"https:\/\/drive.google.com\/file\/d\/1P0-WgZIPiNha98lGJnPMv9smG83k1nbt\/preview","Genero":"Ficcao cientifica, Aventura ","Idade":"14","Ano":"2014","Legenda":"0","foto":"161739032260676af211a10.png","fotogrande":"161739032260676af2077f5.png","banner":"161739032160676af1ef603.png"},"93":{"ID":"200","Nome":"Jogos Vorazes - A Esperan\u00e7a O Final","Link":"https:\/\/drive.google.com\/file\/d\/10MQFqDxmmwtQw-qEyX6Y5SE7H8B7Kktg\/preview","Genero":"Ficcao Cientifica, Action","Idade":"14","Ano":"2015","Legenda":"0","foto":"161740367860679f1ea4fcd.png","fotogrande":"161740367860679f1e9bb3e.png","banner":"161740367860679f1e8f6d1.png"},"94":{"ID":"198","Nome":"Jogos Vorazes - Em Chamas","Link":"https:\/\/drive.google.com\/file\/d\/1choQ0HwnT6uZ83oXgy5FSl_-iunilWpR\/preview","Genero":"Ficcao cientifica, Aventura","Idade":"14","Ano":"2013","Legenda":"0","foto":"161738920060676690ac787.png","fotogrande":"161738920060676690a1f54.png","banner":"1617389200606766909631b.png"},"95":{"ID":"73","Nome":"Jojo Rabbit","Link":"https:\/\/drive.google.com\/file\/d\/1PecC4otuET9uO1_lDRsm-7z2DLzkHgZM\/preview","Genero":"Comedia, Guerra, Drama","Idade":"14","Ano":"2019","Legenda":"0","foto":"15941463225f04be12cc887.png","fotogrande":"15941463225f04be12cc887.png","banner":null},"96":{"ID":"185","Nome":"Jumanji - Bem Vindo a Selva","Link":"https:\/\/drive.google.com\/file\/d\/1XyLFcGmmwbpQvDCilgYleO_h5b6W6KWb\/preview","Genero":"Comedia, Aventura","Idade":"12","Ano":"2017","Legenda":"0","foto":"1614696225603e4f21b02df.png","fotogrande":"1614696225603e4f21a5ecc.png","banner":"1614696225603e4f219c335.png"},"97":{"ID":"36","Nome":"Jumanji: Proxima Fase","Link":"https:\/\/drive.google.com\/file\/d\/1jNbRwC1dkGQE6_5OxPLha9QC-GlTgml_\/preview","Genero":"Aventura, Comedia, Fantasia","Idade":"12","Ano":"2019","Legenda":"0","foto":"15906078785ecec0062ff12.png","fotogrande":"15906078785ecec0062ff12.png","banner":null},"98":{"ID":"17","Nome":"Jumper","Link":"https:\/\/drive.google.com\/file\/d\/1MB09OXJZl67_PMtJh2gO12qw7YOCfDCR\/preview","Genero":"Action, Aventura, Ficcao cientifica","Idade":"12","Ano":"2008","Legenda":"1","foto":"15874245405e9e2d1cee371.png","fotogrande":"15874245405e9e2d1cee371.png","banner":null},"99":{"ID":"214","Nome":"Jungle Cruise","Link":"https:\/\/drive.google.com\/file\/d\/1DjrIzQc7m8ZTSLTHyv7CzGk58OQjksAo\/preview","Genero":" Aventura, Fantasia","Idade":"12","Ano":"2021","Legenda":"0","foto":"1628799737611582f96faeb.png","fotogrande":"1628799737611582f94cd34.png","banner":"1628799737611582f92b811.png"},"100":{"ID":"204","Nome":"Kim Possible - O Filme","Link":"https:\/\/drive.google.com\/file\/d\/1ZsDGN37_deYN_epcP3Skd9McvLs7VbIN\/preview","Genero":"Aventura, Comedia","Idade":"Livre","Ano":"2019","Legenda":"0","foto":"1617730064606c9a10a9eba.png","fotogrande":"1617730064606c9a109ca99.png","banner":"1617730061606c9a0d592f4.png"},"101":{"ID":"150","Nome":"Kingsglaive - Final Fantasy XV","Link":"https:\/\/drive.google.com\/file\/d\/1yXtLlIzmsEIIUuhnBVG6jz-nHEO1LfHU\/preview","Genero":"Fantasia, Action","Idade":"14","Ano":"2016","Legenda":"1","foto":"16105037915ffe566f71f99.png","fotogrande":"16105037915ffe566f78ef9.png","banner":"16105037915ffe566f6602f.png"},"102":{"ID":"115","Nome":"Kung Fu Panda","Link":"https:\/\/drive.google.com\/file\/d\/1vgNt1Rr_tC6f-RKtOBgMlNDhpmr9X65_\/preview","Genero":"Animacao, Infantil","Idade":"Livre","Ano":"2008","Legenda":"1","foto":"16042529215f9ef4f9c7e5f.png","fotogrande":"16042529215f9ef4f9c7e5f.png","banner":null},"103":{"ID":"116","Nome":"Kung Fu Panda 2","Link":"https:\/\/drive.google.com\/file\/d\/1n7Wi4KaORWfZ9j-3QnD7nBdUFjLDhKRj\/preview","Genero":"Animacao ,Comedia","Idade":"Livre","Ano":"2011","Legenda":"1","foto":"16042533315f9ef69307c60.png","fotogrande":"16042533315f9ef69307c60.png","banner":null},"104":{"ID":"117","Nome":"Kung Fu Panda 3","Link":"https:\/\/drive.google.com\/file\/d\/1drK35ynt7EcdIStxUkErJX-4nI1aYI1e\/preview","Genero":"Animacao, Infantil","Idade":"Livre","Ano":"2016","Legenda":"1","foto":"16042539985f9ef92e007e1.png","fotogrande":"16042539985f9ef92e007e1.png","banner":null},"105":{"ID":"130","Nome":"Lado a Lado","Link":"https:\/\/drive.google.com\/file\/d\/1BmhyVPUmF_BuxAD2Q5R44-nWblTmBNVP\/preview","Genero":"Drama, Romance","Idade":"10","Ano":"1998","Legenda":"0","foto":"16067621065fc53e7a7037f.png","fotogrande":"16067621065fc53e7a7037f.png","banner":null},"106":{"ID":"59","Nome":"Lego DC Shazam -  Magia e Monstros","Link":"https:\/\/drive.google.com\/file\/d\/1CPrhW6RIwtkh7LrmwuY-YMlAZ9Zy4DWm\/preview","Genero":"Action, Aventura, Animacao, Comedia, Familia, Ficcao cientifica","Idade":"Livre","Ano":"2020","Legenda":"0","foto":"15923518445ee95c64828e2.png","fotogrande":"15923518445ee95c64828e2.png","banner":null},"107":{"ID":"114","Nome":"Liga da Justi\u00e7a","Link":"https:\/\/drive.google.com\/file\/d\/1_3H0DBIyFcekZcDfW3s6lNwxOKXPXU29\/preview","Genero":"Action, Aventura","Idade":"12","Ano":"2017","Legenda":"0","foto":"16040769525f9c4598a469e.png","fotogrande":"16040769525f9c4598a469e.png","banner":null},"108":{"ID":"81","Nome":"Liga da Justica Sombria","Link":"https:\/\/drive.google.com\/file\/d\/1xAhMB1NEkFZn8S3EbXmzdPZ7If-pVTMh\/preview","Genero":"Animacao, Action, Aventura","Idade":"14","Ano":"2017","Legenda":"0","foto":"15966443415f2adbf500109.png","fotogrande":"15966443415f2adbf500109.png","banner":null},"109":{"ID":"131","Nome":"Lino - Uma Aventura de Sete Vidas","Link":"https:\/\/drive.google.com\/file\/d\/19HjLollySo9UiwwFm7InTx9JRRPN23OY\/preview","Genero":"Comedia, Animacao","Idade":"Livre","Ano":"2017","Legenda":"0","foto":"16067623395fc53f630edad.png","fotogrande":"16067623395fc53f630edad.png","banner":null},"110":{"ID":"215","Nome":"Luca","Link":"https:\/\/drive.google.com\/file\/d\/1H_LPE4R4JdyI0QGuwkOS-2pk6_Mjfcsc\/preview","Genero":"Comedia, Aventura","Idade":"Livre","Ano":"2021","Legenda":"0","foto":"1628805562611599bac9f99.png","fotogrande":"1628805562611599bac659c.png","banner":"1628805562611599babe422.png"},"111":{"ID":"186","Nome":"Lucy","Link":"https:\/\/drive.google.com\/file\/d\/1QS5h862AsMqK_CEBelVtC1Edfs6tSz6x\/preview","Genero":"Action, Ficcao cientifica","Idade":"16","Ano":"2014","Legenda":"0","foto":"1614696663603e50d74d6b9.png","fotogrande":"1614696663603e50d74313b.png","banner":"1614696663603e50d73c007.png"},"112":{"ID":"56","Nome":"Lupin III: O Primeiro","Link":"https:\/\/drive.google.com\/file\/d\/1Lx0022mBq6-7eY0SEmXOaBUlPYJHPM4V\/preview","Genero":"Aventura, Action, Animacao","Idade":"Livre","Ano":"2019","Legenda":"0","foto":"15922742335ee82d39d1242.png","fotogrande":"15922742335ee82d39d1242.png","banner":null},"113":{"ID":"100","Nome":"Maldita Sorte","Link":"https:\/\/drive.google.com\/file\/d\/1-Vj6SnKIEw76K1-SuNu5rg0sm5-9mvu0\/preview","Genero":"Comedia","Idade":"18","Ano":"2007","Legenda":"0","foto":"16014186935f73b5c53fb3f.png","fotogrande":"16014186935f73b5c53fb3f.png","banner":null},"114":{"ID":"209","Nome":"Malevola","Link":"https:\/\/drive.google.com\/file\/d\/1KptQzBOFOwOpOZhVLWTd6kTk9bRhzsnL\/preview","Genero":"Fantasia, Aventura, Action","Idade":"10","Ano":"2014","Legenda":"0","foto":"1617732508606ca39c8dfd9.png","fotogrande":"1617732508606ca39c8391d.png","banner":"1617732508606ca39c77c80.png"},"115":{"ID":"208","Nome":"Malevola - Dona do Mal","Link":"https:\/\/drive.google.com\/file\/d\/1D0encsSZ-HCcwYmgsjELE-KmzMIiz-aE\/preview","Genero":"Fantasia, Action","Idade":"10","Ano":"2019","Legenda":"0","foto":"1617732101606ca2056756d.png","fotogrande":"1617732101606ca2055e0de.png","banner":"1617732101606ca20554090.png"},"116":{"ID":"170","Nome":"Maos Talentosas - A Historia de Ben Carson","Link":"https:\/\/drive.google.com\/file\/d\/1xkGhi29_hVwjFB_xf1tjuTWOa8cZ4DuP\/preview","Genero":"Drama, Gospel","Idade":"12","Ano":"2009","Legenda":"1","foto":"1613522778602c675a0329d.png","fotogrande":"1613522777602c6759d0230.png","banner":"1613522777602c6759a9e29.png"},"117":{"ID":"25","Nome":"Maria e Joao: O Conto Das Bruxas","Link":"https:\/\/drive.google.com\/file\/d\/1LGNhznOn2Oacj3ty3HmW6rJDaZq6dRLM\/preview","Genero":"Terror, Fantasia, Thriller","Idade":"14","Ano":"2020","Legenda":"1","foto":"15882998285eab88346ccce.png","fotogrande":"15882998285eab88346ccce.png","banner":null},"118":{"ID":"154","Nome":"Matrix","Link":"https:\/\/drive.google.com\/file\/d\/1K1mkmEL6ou2rQ31d2tY5-eyqTZS095q8\/preview","Genero":"Ficcao cientifica, Action","Idade":"14","Ano":"1999","Legenda":"1","foto":"16118525296012eaf1a76f4.png","fotogrande":"16118525296012eaf19dc42.png","banner":"16118525296012eaf1950b6.png"},"119":{"ID":"132","Nome":"Melancolia","Link":"https:\/\/drive.google.com\/file\/d\/1DQucHq6M3DA6mUS8nPxl3QhkLpJMS9X8\/preview","Genero":"Drama, Ficcao cientifica","Idade":"14","Ano":"2011","Legenda":"0","foto":"16067625345fc54026eba45.png","fotogrande":"16067625345fc54026eba45.png","banner":null},"120":{"ID":"133","Nome":"Meu Primeiro Amor","Link":"https:\/\/drive.google.com\/file\/d\/1GxlVhpt-lVE0kS_wnqkvCmbW4R1QcnJS\/preview","Genero":"Drama, Infantil","Idade":"Livre","Ano":"1991","Legenda":"0","foto":"16067629065fc5419ad1222.png","fotogrande":"16067629065fc5419ad1222.png","banner":null},"121":{"ID":"72","Nome":"Midway - Batalha Em Alto Mar","Link":"https:\/\/drive.google.com\/file\/d\/1gclNWNx8xpFWdbcpp2VUVzVj3KoeOMl8\/preview","Genero":"Guerra, Historia, Action, Drama","Idade":"14","Ano":"2019","Legenda":"0","foto":"15940874495f03d81990c4e.png","fotogrande":"15940874495f03d81990c4e.png","banner":null},"122":{"ID":"78","Nome":"Milagre Na Cela 7","Link":"https:\/\/drive.google.com\/file\/d\/1ilr2VGu-w41cajb9Kq7-CiG5j6I3PDf9\/preview","Genero":"Drama, Comedia, Familia, Gospel","Idade":"Livre","Ano":"2019","Legenda":"0","foto":"15957319305f1cefda0b2ea.png","fotogrande":"15957319305f1cefda0b2ea.png","banner":null},"123":{"ID":"35","Nome":"Minha Mae E Uma Pe\u00e7a 3","Link":"https:\/\/drive.google.com\/file\/d\/1OII7pm8IdGEgxNQapzAu3XSgJq80sLHU\/preview","Genero":"Comedia","Idade":"12","Ano":"2019","Legenda":"0","foto":"15893446095ebb79614c18e.png","fotogrande":"15893446095ebb79614c18e.png","banner":null},"124":{"ID":"223","Nome":"Miraculous World Xangai - A Lenda de LadyDragon","Link":"https:\/\/drive.google.com\/file\/d\/1Ij4ZBXfdGgGI7E2F8TJCRzCM0_fFzKKW\/preview","Genero":"Animacao, Comedia, Familia, Aventura","Idade":"Livre","Ano":"2021","Legenda":"0","foto":"16310535436137e6e79c537.png","fotogrande":"16310535436137e6e7848d4.png","banner":"16310535436137e6e76dd92.png"},"125":{"ID":"178","Nome":"Missao Impossivel - Efeito Fallout","Link":"https:\/\/drive.google.com\/file\/d\/1mkptF750zWH9xNc8m6Y9efAYAkn8ft_P\/preview","Genero":"Action, Aventura","Idade":"14","Ano":"2018","Legenda":"0","foto":"161404051560344dc360415.png","fotogrande":"161404051560344dc3551ea.png","banner":"161404051560344dc34d3aa.png"},"126":{"ID":"82","Nome":"Moana - Um Mar De Aventuras","Link":"https:\/\/drive.google.com\/file\/d\/1mlQsDH6Egfd7zFJ6Qz9GIf7X8VBoIJKF\/preview","Genero":"Aventura, Comedia, Familia, Animacao","Idade":"Livre","Ano":"2016","Legenda":"0","foto":"15966448375f2adde55105a.png","fotogrande":"15966448375f2adde55105a.png","banner":null},"127":{"ID":"9","Nome":"Mortal Kombat Legends: A Vinganca De Scorpion","Link":"https:\/\/drive.google.com\/file\/d\/1ppH1UIudASDgHdtNPpi_frmQtKbkyOaS\/preview","Genero":"Fantasia, Action, Aventura, Animacao","Idade":"18","Ano":"2020","Legenda":"1","foto":"15869071155e9647eb0c0dc.png","fotogrande":"15869071155e9647eb0c0dc.png","banner":null},"128":{"ID":"94","Nome":"Mulan","Link":"https:\/\/drive.google.com\/file\/d\/14H8qxV20W7xRYYndl9kNQpYtFUlo3Clz\/preview","Genero":"Drama, Action, Guerra, Fantasia","Idade":"13","Ano":"2020","Legenda":"0","foto":"15995859585f57bea6390ea.png","fotogrande":"15995859585f57bea6390ea.png","banner":null},"129":{"ID":"165","Nome":"Mulher-Maravilha 1984","Link":"https:\/\/drive.google.com\/file\/d\/13BiZIhTqn8pZohjeRkMYnKfUQx3ojgbC\/preview","Genero":"Fantasia, Action, Aventura","Idade":"12","Ano":"2020","Legenda":"0","foto":"16129774836024154b7115e.png","fotogrande":"16129774836024154b5fff6.png","banner":"16129774836024154b4e9e2.png"},"130":{"ID":"41","Nome":"My Hero Academia - Dois Herois","Link":"https:\/\/drive.google.com\/file\/d\/1HGD36QajxXi994S9yO6FMcV7127N835w\/preview","Genero":"Animacao, Action","Idade":"12","Ano":"2019","Legenda":"0","foto":"15908070785ed1ca26308e9.png","fotogrande":"15908070785ed1ca26308e9.png","banner":null},"131":{"ID":"102","Nome":"Nasce Uma Estrela","Link":"https:\/\/drive.google.com\/file\/d\/1KPyIFgIJZrBS6v22m2XkRMKz_54XLrKu\/preview","Genero":"Romance, Musica","Idade":"12","Ano":"2018","Legenda":"0","foto":"16030585765f8cbb905bd1b.png","fotogrande":"16030585765f8cbb905bd1b.png","banner":null},"132":{"ID":"95","Nome":"Nem que a Vaca Tussa","Link":"https:\/\/drive.google.com\/file\/d\/1pRNJeJbAx8a7dpIxtg-dhw7NPC82BmdX\/preview","Genero":"Animacao, Infantil","Idade":"Livre","Ano":"2004","Legenda":"0","foto":"15995861715f57bf7b7afb8.png","fotogrande":"15995861715f57bf7b7afb8.png","banner":null},"133":{"ID":"134","Nome":"O Bom Dinossauro","Link":"https:\/\/drive.google.com\/file\/d\/1I7AvuVk6BUcsEQ2p2xDkfZ2eZueGSqu_\/preview","Genero":"Infantil, Aventura","Idade":"Livre","Ano":"2015","Legenda":"0","foto":"16067634055fc5438d859e9.png","fotogrande":"16067634055fc5438d859e9.png","banner":null},"134":{"ID":"135","Nome":"O Bom Gigante Amigo","Link":"https:\/\/drive.google.com\/file\/d\/1lurMaBg_9WtfzyzFA9LAGNfaWeJ804nN\/preview","Genero":"Fantasia, Infantil","Idade":"Livre","Ano":"2016","Legenda":"0","foto":"16067636385fc5447612dfa.png","fotogrande":"16067636385fc5447612dfa.png","banner":null},"135":{"ID":"216","Nome":"O Chapeleiro Louco","Link":"https:\/\/drive.google.com\/file\/d\/1zxWaneeTsiMMBT58dkj-qzGfa5D0jr3Y\/preview","Genero":"Thriller, Terror","Idade":"16","Ano":"2021","Legenda":"0","foto":"162880614061159bfc5ae52.png","fotogrande":"162880614061159bfc56d12.png","banner":"162880614061159bfc501f3.png"},"136":{"ID":"19","Nome":"O Destemido","Link":"https:\/\/drive.google.com\/file\/d\/1fay4lb82zgcACRb6-dCOzzMJZnMfPLDA\/preview","Genero":"Action, Fantasia","Idade":"16","Ano":"2010","Legenda":"0","foto":"15874346665e9e54aac86de.png","fotogrande":"15874346665e9e54aac86de.png","banner":null},"137":{"ID":"74","Nome":"O Ditador","Link":"https:\/\/drive.google.com\/file\/d\/1GqpTtIMaNeabVDiFOVgtVRtjcbSuY1Fl\/preview","Genero":"Comedia, Humor negro","Idade":"14","Ano":"2012","Legenda":"0","foto":"15941794675f053f8b0c6c7.png","fotogrande":"15941794675f053f8b0c6c7.png","banner":null},"138":{"ID":"217","Nome":"O Esquadr\u00e3o Suicida 2","Link":"https:\/\/drive.google.com\/file\/d\/1hty_REg_vtHOPH2Q0igzTmOz2LXKpxt8\/preview","Genero":"Action, Aventura","Idade":"16","Ano":"2021","Legenda":"0","foto":"162880663161159de74f42c.png","fotogrande":"162880663161159de748ad9.png","banner":"162880663161159de742ab0.png"},"139":{"ID":"136","Nome":"O Impossivel","Link":"https:\/\/drive.google.com\/file\/d\/1X5anGyOI62ZYtXnkl4HjuGWe8WfM_fT1\/preview","Genero":"Drama","Idade":"12","Ano":"2012","Legenda":"0","foto":"16067639025fc5457ea3e85.png","fotogrande":"16067639025fc5457ea3e85.png","banner":null},"140":{"ID":"194","Nome":"O Lado Bom da Vida","Link":"https:\/\/drive.google.com\/file\/d\/1vYwC9FtvzDwmuOoHgKFIMXbdOXcSjzBG\/preview","Genero":"Romance, Comedia","Idade":"12","Ano":"2012","Legenda":"0","foto":"161628487560568ccbe2596.png","fotogrande":"161628487560568ccbd7e88.png","banner":"161628487560568ccbce646.png"},"141":{"ID":"8","Nome":"O Lar das Criancas Peculiares","Link":"https:\/\/drive.google.com\/file\/d\/1RnjuDc1rdw-B1BTtPQTu4kx_HPfJ_ckh\/preview","Genero":"Drama, Fantasia, Aventura, Familia","Idade":"12","Ano":"2016","Legenda":"0","foto":"15869070435e9647a397bc4.png","fotogrande":"15869070435e9647a397bc4.png","banner":null},"142":{"ID":"179","Nome":"O Mapa das Pequenas Coisas Perfeitas","Link":"https:\/\/drive.google.com\/file\/d\/1Fc4Zcbt2HlNNRi6vR7u7zD7oxuhcAwPt\/preview","Genero":"Drama","Idade":"12","Ano":"2021","Legenda":"0","foto":"161404102060344fbc98a06.png","fotogrande":"161404102060344fbc8d18c.png","banner":"161404102060344fbc84ef9.png"},"143":{"ID":"203","Nome":"O Massacre da Serra Eletrica","Link":"https:\/\/drive.google.com\/file\/d\/1Yr7LSLlx4CRuYkQWnxH-E7C_etGHdyEq\/preview","Genero":"Terror","Idade":"18","Ano":"2003","Legenda":"0","foto":"1617729576606c982871b21.png","fotogrande":"1617729576606c9828698ac.png","banner":"1617729576606c982860e06.png"},"144":{"ID":"137","Nome":"O Menino do Pijama Listrado","Link":"https:\/\/drive.google.com\/file\/d\/1wZSS2HgxROFdkIYnyDmkyZNdVH3cZRrC\/preview","Genero":"Guerra, Drama","Idade":"12","Ano":"2018","Legenda":"0","foto":"16067641115fc5464f487ba.png","fotogrande":"16067641115fc5464f487ba.png","banner":null},"145":{"ID":"197","Nome":"O Novi\u00e7o Rebelde","Link":"https:\/\/drive.google.com\/file\/d\/1ZfhWzO5HU3tfx0INn0sSmV2PUsZc411K\/preview","Genero":"Comedia, Infantil","Idade":"Livre","Ano":"1997","Legenda":"0","foto":"1616593048605b4098eb0d5.png","fotogrande":"1616593048605b4098dba53.png","banner":"1616593048605b4098ca5a6.png"},"146":{"ID":"43","Nome":"O Po\u00e7o","Link":"https:\/\/drive.google.com\/file\/d\/1jufwSlmGrALpB77t8-SW8TmRAF-AdvvB\/preview","Genero":"Drama, Ficcao cientifica","Idade":"12","Ano":"2019","Legenda":"0","foto":"15908076525ed1cc64006e1.png","fotogrande":"15908076525ed1cc64006e1.png","banner":null},"147":{"ID":"4","Nome":"O Poder e o Impossivel","Link":"https:\/\/drive.google.com\/file\/d\/1scdO5sXEoRI5m-BCBGWZd-ayvNMn-nZf\/preview","Genero":"Aventura, Biografia, Drama, Gospel","Idade":"14","Ano":"2017","Legenda":"0","foto":"15872639735e9bb9e539f69.png","fotogrande":"15872639735e9bb9e539f69.png","banner":null},"148":{"ID":"180","Nome":"O Principe Esquecido","Link":"https:\/\/drive.google.com\/file\/d\/15JspRB0WZOhSaRzABFdoz2St1riGOd3G\/preview","Genero":"Comedia, Fantasia","Idade":"10","Ano":"2020","Legenda":"0","foto":"16140416926034525ca3793.png","fotogrande":"16140416926034525c98ebf.png","banner":"16140416926034525c8f9f0.png"},"149":{"ID":"101","Nome":"O Quarto Secreto","Link":"https:\/\/drive.google.com\/file\/d\/1LKCidP_W9MXEhabBghDGYArx-ACkj__x\/preview","Genero":"Drama, Thriller","Idade":"14","Ano":"2014","Legenda":"1","foto":"16015692665f7601f212b3f.png","fotogrande":"16015692665f7601f212b3f.png","banner":null},"150":{"ID":"71","Nome":"O Rei","Link":"https:\/\/drive.google.com\/file\/d\/1wkdND_IzfjdGMdN5lfPDVc1WSaYM2GxL\/preview","Genero":"Drama, Historia, Guerra","Idade":"18","Ano":"2019","Legenda":"0","foto":"15940871995f03d71f4484d.png","fotogrande":"15940871995f03d71f4484d.png","banner":null},"151":{"ID":"31","Nome":"O Reino Gelado - A Terra Dos Espelhos","Link":"https:\/\/drive.google.com\/file\/d\/1VlU1bEIpwqAXiECbstO01xALOqQT-r04\/preview","Genero":"Animacao, Aventura, Comedia, Familia, Fantasia","Idade":"Livre","Ano":"2018","Legenda":"0","foto":"15891710805eb8d38812a21.png","fotogrande":"15891710805eb8d38812a21.png","banner":null},"152":{"ID":"181","Nome":"Oito Mulheres e um Segredo","Link":"https:\/\/drive.google.com\/file\/d\/1QLR1bb7vnbl9SCLfWHY4Eg3EJOD2Ld0M\/preview","Genero":"Comedia, Crime","Idade":"14","Ano":"2018","Legenda":"0","foto":"16140426866034563e064d9.png","fotogrande":"16140426856034563df190d.png","banner":"16140426856034563de71c9.png"},"153":{"ID":"15","Nome":"Os Par\u00e7as 2","Link":"https:\/\/drive.google.com\/file\/d\/1Eze7gtVy9fJZccfE-jVGfZJYeoMJmjNW\/preview","Genero":"Comedia","Idade":"14","Ano":"2019","Legenda":"1","foto":"15874166785e9e0e66e0adf.png","fotogrande":"15874166785e9e0e66e0adf.png","banner":null},"154":{"ID":"86","Nome":"Os Simpsons - O Filme","Link":"https:\/\/drive.google.com\/file\/d\/1x8Bbs46Hb-NHrNAiNQWHMiPTCLi0o7Ow\/preview","Genero":"Animacao, Comedia, Familia","Idade":"12","Ano":"2007","Legenda":"0","foto":"15967327835f2c356fa8f72.png","fotogrande":"15967327835f2c356fa8f72.png","banner":null},"155":{"ID":"96","Nome":"Paixao Sem Limites","Link":"https:\/\/drive.google.com\/file\/d\/1NDEqovvrHedzb8BFQPFXpiyTXQ93oxG1\/preview","Genero":"Romance, Drama","Idade":"16","Ano":"2010","Legenda":"0","foto":"16005619545f66a32244508.png","fotogrande":"16005619545f66a32244508.png","banner":null},"156":{"ID":"167","Nome":"Para todos os garotos - Agora e para sempre","Link":"https:\/\/drive.google.com\/file\/d\/1hNcIFnqTlyA863bXuycbiZ_VgdvnRCwn\/preview","Genero":"Romance, Comedia","Idade":"14","Ano":"2021","Legenda":"0","foto":"1613520816602c5fb00c9b3.png","fotogrande":"1613520816602c5fb0163b3.png","banner":"1613520816602c5fb001cad.png"},"157":{"ID":"57","Nome":"Para Todos Os Garotos - PS Ainda Amo Voce","Link":"https:\/\/drive.google.com\/file\/d\/1ur9rnpB-Aj7eS3o7wCqMid8MEQHerhOd\/preview","Genero":"Romance, Comedia","Idade":"12","Ano":"2020","Legenda":"0","foto":"15922759245ee833d4b3686.png","fotogrande":"15922759245ee833d4b3686.png","banner":null},"158":{"ID":"44","Nome":"Parasita","Link":"https:\/\/drive.google.com\/file\/d\/1DXzQGb6g6RvtnMuX9s3GbyL5sFN8Z2_l\/preview","Genero":"Comedia, Thriller, Drama","Idade":"16","Ano":"2019","Legenda":"0","foto":"15908078205ed1cd0ceff68.png","fotogrande":"15908078205ed1cd0ceff68.png","banner":null},"159":{"ID":"138","Nome":"Patch Adams - O amor e contagioso","Link":"https:\/\/drive.google.com\/file\/d\/1qRzQ_c7XWUhdfpjRYr-Ysrx187hERccu\/preview","Genero":"Drama, Comedia","Idade":"12","Ano":"1998","Legenda":"0","foto":"16067643415fc54735e2a2e.png","fotogrande":"16067643415fc54735e2a2e.png","banner":null},"160":{"ID":"90","Nome":"Perdido Em Marte","Link":"https:\/\/drive.google.com\/file\/d\/11sYUKSCKpUV6SHx1VEcXNuYAj8vqZQuh\/preview","Genero":"Drama, Aventura, Ficcao cientifica","Idade":"12","Ano":"2015","Legenda":"0","foto":"15970298635f30bde742497.png","fotogrande":"15970298635f30bde742497.png","banner":null},"161":{"ID":"64","Nome":"Piratas Do Caribe - A Maldi\u00e7ao Do Perola Negra","Link":"https:\/\/drive.google.com\/file\/d\/1zvw3kf50rwQFi9MkRdYSNQyrDtFqBg6b\/preview","Genero":"Aventura, Fantasia, Action","Idade":"14","Ano":"2003","Legenda":"0","foto":"15937313865efe693ad48a7.png","fotogrande":"15937313865efe693ad48a7.png","banner":null},"162":{"ID":"67","Nome":"Piratas Do Caribe - A Vingan\u00e7a De Salazar","Link":"https:\/\/drive.google.com\/file\/d\/1gx7T1bfjRa4qXw2dA4eLTuZR1Tv5kXZj\/preview","Genero":"Aventura, Action, Fantasia, Comedia","Idade":"12","Ano":"2017","Legenda":"0","foto":"15937324225efe6d46a3433.png","fotogrande":"15937324225efe6d46a3433.png","banner":null},"163":{"ID":"66","Nome":"Piratas Do Caribe - Navegando Em Aguas Misteriosas","Link":"https:\/\/drive.google.com\/file\/d\/1dKhGt4wd_jJaow_5EaKlqIxWhpDHKL73\/preview","Genero":"Aventura, Action, Fantasia","Idade":"12","Ano":"2011","Legenda":"0","foto":"15937320835efe6bf350250.png","fotogrande":"15937320835efe6bf350250.png","banner":null},"164":{"ID":"68","Nome":"Piratas Do Caribe - No Fim Do Mundo","Link":"https:\/\/drive.google.com\/file\/d\/1bJs2VeL8CT4b8yZh3cMNYx_-IN8KOrFf\/preview","Genero":"Aventura, Fantasia, Action","Idade":"12","Ano":"2007","Legenda":"0","foto":"37431455159efe9729ed00d.png","fotogrande":"37431455159efe9729ed00d.png","banner":null},"165":{"ID":"65","Nome":"Piratas Do Caribe - O Bau Da Morte","Link":"https:\/\/drive.google.com\/file\/d\/18EmMJF3r-8fTEZKx6UdyZcX6tmTrkNQj\/preview","Genero":"Aventura, Fantasia, Action","Idade":"12","Ano":"2006","Legenda":"0","foto":"15937317805efe6ac486bcd.png","fotogrande":"15937317805efe6ac486bcd.png","banner":null},"166":{"ID":"5","Nome":"Pokemon - Mewtwo Contra-Ataca","Link":"https:\/\/drive.google.com\/file\/d\/1aiLR94eQAY4oFCeTNhCIVr2rSePmZJtH\/preview","Genero":"Animacao, Action, Familia","Idade":"Livre","Ano":"2019","Legenda":"0","foto":"15869067095e96465578ce5.png","fotogrande":"15869067095e96465578ce5.png","banner":null},"167":{"ID":"112","Nome":"Principe da Persia - As areias do tempo","Link":"https:\/\/drive.google.com\/file\/d\/15VQYGQ4BRvbeYA392HtzSUecorGov3PE\/preview","Genero":"Action, Aventura","Idade":"12","Ano":"2010","Legenda":"0","foto":"16037674245f978c8013362.png","fotogrande":"16037674245f978c8013362.png","banner":null},"168":{"ID":"139","Nome":"Quem Quer Ser um Milionario","Link":"https:\/\/drive.google.com\/file\/d\/1LDL99_ZFFgZGD5_QhadHBvPTd3BrxYb9\/preview","Genero":"Drama, Romance","Idade":"16","Ano":"2008","Legenda":"0","foto":"16067645525fc5480894b9a.png","fotogrande":"16067645525fc5480894b9a.png","banner":null},"169":{"ID":"201","Nome":"Questao de Tempo","Link":"https:\/\/drive.google.com\/file\/d\/1b9QHz3EyXUXQEeCH7rcMyhAd78WxCA5D\/preview","Genero":"Romance, Fantasia","Idade":"12","Ano":"2013","Legenda":"0","foto":"161740387660679fe4d763c.png","fotogrande":"161740387660679fe4cf291.png","banner":"161740387660679fe4c5945.png"},"170":{"ID":"218","Nome":"Rango","Link":"https:\/\/drive.google.com\/file\/d\/1CQxpKik3xC3MjywkI-o2k7hlWA7CFhp5\/preview","Genero":"Familia, Comedia","Idade":"10","Ano":"2011","Legenda":"0","foto":"16288077956115a2739cf8d.png","fotogrande":"16288077956115a27395f72.png","banner":"16288077956115a2738f931.png"},"171":{"ID":"191","Nome":"Raya e o Ultimo Dragao","Link":"https:\/\/drive.google.com\/file\/d\/1pIgunYsBiwF2eKxQHEw-_9BxDyvs2JNy\/preview","Genero":"Aventura, Fantasia","Idade":"10","Ano":"2021","Legenda":"1","foto":"16154263186049730ec0cd2.png","fotogrande":"16154263186049730eb63e9.png","banner":"16154263186049730eab69f.png"},"172":{"ID":"22","Nome":"Resgate","Link":"https:\/\/drive.google.com\/file\/d\/11tVKjPTXk8FFAnUfn81JX2zMn8NkOpls\/preview","Genero":"Action, Thriller","Idade":"16","Ano":"2020","Legenda":"0","foto":"15877832625ea3a65e9163a.png","fotogrande":"15877832625ea3a65e9163a.png","banner":null},"173":{"ID":"182","Nome":"Resident Evil 5 - Retribuicao","Link":"https:\/\/drive.google.com\/file\/d\/1EQwocF8S-2-nflLmLVxIOKmYSBMA-vfA\/preview","Genero":"Action, Terror","Idade":"16","Ano":"2012","Legenda":"0","foto":"16140431716034582340a5a.png","fotogrande":"161404317160345823361e8.png","banner":"1614043171603458232b305.png"},"174":{"ID":"70","Nome":"Sargento Stubby","Link":"https:\/\/drive.google.com\/file\/d\/1M18PtDjSb_fff3Iwd0MKN13evWOLMkeD\/preview","Genero":"Animacao, Aventura, Fam\u00c3\u00adlia, Historia, Guerra","Idade":"12","Ano":"2018","Legenda":"0","foto":"15940869985f03d656e9b2f.png","fotogrande":"15940869985f03d656e9b2f.png","banner":null},"175":{"ID":"93","Nome":"Scooby! O Filme","Link":"https:\/\/drive.google.com\/file\/d\/1Q510FtilTDphrANyjpuSH496bojAdryL\/preview","Genero":"Familia, Animacao, Comedia, Misterio, Aventura","Idade":"Livre","Ano":"2020","Legenda":"0","foto":"15970305845f30c0b8153cd.png","fotogrande":"15970305845f30c0b8153cd.png","banner":null},"176":{"ID":"187","Nome":"Scooby-Doo e a Espada","Link":"https:\/\/drive.google.com\/file\/d\/1kpjOiQ_VJesWIS30peXDCe8gZxbJ_0Pl\/preview","Genero":"Animacao, Comedia, Familia, Misterio, Aventura","Idade":"Livre","Ano":"2021","Legenda":"0","foto":"1614697228603e530c7f316.png","fotogrande":"1614697228603e530c74a41.png","banner":"1614697228603e530c6b6d5.png"},"177":{"ID":"155","Nome":"Seguranca Nacional","Link":"https:\/\/drive.google.com\/file\/d\/1smmgrBB5Krz9UQZCOb8NW_5iBhOfpuMT\/preview","Genero":"Comedia, Action, Crime","Idade":"12","Ano":"2003","Legenda":"0","foto":"161212400460170f64345ff.png","fotogrande":"161212400460170f642b96d.png","banner":"161212400460170f641e699.png"},"178":{"ID":"190","Nome":"Sem Limites","Link":"https:\/\/drive.google.com\/file\/d\/1mDjCU0IfcbxouWexya7kbGa39jDogtEV\/preview","Genero":"Thriller, Action","Idade":"14","Ano":"2011","Legenda":"1","foto":"1614727558603ec986b6135.png","fotogrande":"1614727558603ec986a9d0f.png","banner":"1614727558603ec9869c449.png"},"179":{"ID":"140","Nome":"Sempre ao Seu Lado","Link":"https:\/\/drive.google.com\/file\/d\/1kbuESniPDkTqqngr8jO_gpLJZQtpybSA\/preview","Genero":"Drama","Idade":"Livre","Ano":"2009","Legenda":"0","foto":"16067648145fc5490e0aa08.png","fotogrande":"16067648145fc5490e0aa08.png","banner":"16067648145fc5490e0aa08.png"},"180":{"ID":"141","Nome":"Sete Vidas","Link":"https:\/\/drive.google.com\/file\/d\/1GboufYaMpbCfTonBcGjgHzcLu7IFE4lk\/preview","Genero":"Drama, Romance","Idade":"14","Ano":"2008","Legenda":"0","foto":"16067649965fc549c404624.png","fotogrande":"16067649965fc549c404624.png","banner":"16067649965fc549c404624.png"},"181":{"ID":"32","Nome":"Seu Nome - Your Name","Link":"https:\/\/drive.google.com\/file\/d\/1YOFmDraSWSum2km9RpOXM6BUaMsTIzIU\/preview","Genero":" Romance, Animacao, Drama","Idade":"12","Ano":"2016","Legenda":"0","foto":"15892572225eba24065d8b4.png","fotogrande":"15892572225eba24065d8b4.png","banner":null},"182":{"ID":"188","Nome":"Shazam","Link":"https:\/\/drive.google.com\/file\/d\/13Q-ziVziYoGkaZndgPZtGD8hTp7K-6_H\/preview","Genero":"Action, Fantasia","Idade":"12","Ano":"2019","Legenda":"0","foto":"1614697614603e548e29cfa.png","fotogrande":"1614697614603e548e1d0d6.png","banner":"1614697614603e548e12ac1.png"},"183":{"ID":"107","Nome":"Shrek","Link":"https:\/\/drive.google.com\/file\/d\/1_Z5UdG1VVDOFLF47AbBQu81QMsFlrNlj\/preview","Genero":"Fantasia, Aventura, Comedia","Idade":"Livre","Ano":"2001","Legenda":"0","foto":"16032976405f9061687a2b5.png","fotogrande":"16032976405f9061687a2b5.png","banner":null},"184":{"ID":"104","Nome":"Shrek 2","Link":"https:\/\/drive.google.com\/file\/d\/15lRfPouijuXz727qVsWzkSdJusguB8JO\/preview","Genero":"Animacao, Comedia","Idade":"Livre","Ano":"2004","Legenda":"0","foto":"16031198225f8daace69634.png","fotogrande":"16031198225f8daace69634.png","banner":null},"185":{"ID":"106","Nome":"Shrek para Sempre","Link":"https:\/\/drive.google.com\/file\/d\/1qNuNBTnAvOvEp_Xzdzf02btIFnELVNNt\/preview","Genero":"Animacao, Comedia","Idade":"Livre","Ano":"2010","Legenda":"0","foto":"16031204535f8dad458ae4b.png","fotogrande":"16031204535f8dad458ae4b.png","banner":null},"186":{"ID":"105","Nome":"Shrek Terceiro","Link":"https:\/\/drive.google.com\/file\/d\/1qfiyUYWSstrQtRkT4WMsOjgCy22t_GR5\/preview","Genero":"Animacao, Comedia","Idade":"Livre","Ano":"2007","Legenda":"0","foto":"16031201595f8dac1fd9321.png","fotogrande":"16031201595f8dac1fd9321.png","banner":null},"187":{"ID":"193","Nome":"Snyder cut - Liga da Justi\u00e7a","Link":"https:\/\/drive.google.com\/file\/d\/1cYV3SsGIm1MU4OFdPLBM7SSJk0jqdiri\/preview","Genero":"Action, Aventura, Ficcao Cientifica","Idade":"16","Ano":"2021","Legenda":"1","foto":"161620770860555f5c0f792.png","fotogrande":"161620770860555f5c04399.png","banner":"161620770760555f5bec1c1.png"},"188":{"ID":"51","Nome":"Sobrenatural - A Ultima Chave","Link":"https:\/\/drive.google.com\/file\/d\/1Lq1Lk-GzfyPcLpLceErIio6iUCL0U-IS\/preview","Genero":"Misterio, Terror, Thriller","Idade":"14","Ano":"2018","Legenda":"0","foto":"15908152725ed1ea28882cc.png","fotogrande":"15908152725ed1ea28882cc.png","banner":null},"189":{"ID":"29","Nome":"Sociedade dos poetas mortos","Link":"https:\/\/drive.google.com\/file\/d\/1JLoKAynxGfIcIb-zH4NvhqbOQehhEgUA\/preview","Genero":"Comedia, drama","Idade":"12","Ano":"1990","Legenda":"0","foto":"15883931715eacf4d32fd19.png","fotogrande":"15883931715eacf4d32fd19.png","banner":null},"190":{"ID":"69","Nome":"Soldado Anonimo - Lei Do Retorno","Link":"https:\/\/drive.google.com\/file\/d\/19N4lGE9zsqpv6XsA9msKRGhTPUjfnNf2\/preview","Genero":"Guerra, Action, Drama","Idade":"14","Ano":"2019","Legenda":"0","foto":"15940867925f03d588721a9.png","fotogrande":"15940867925f03d588721a9.png","banner":null},"191":{"ID":"23","Nome":"Sonic - O Filme","Link":"https:\/\/drive.google.com\/file\/d\/1S5Bw7VmAqzN722sHdvRwwwjPdWxWxzR0\/preview","Genero":"Action, Ficcao cientifica, Comedia, Familia","Idade":"Livre","Ano":"2020","Legenda":"0","foto":"15877836155ea3a7bf7a8b5.png","fotogrande":"15877836155ea3a7bf7a8b5.png","banner":null},"192":{"ID":"148","Nome":"Soul","Link":"https:\/\/drive.google.com\/file\/d\/1hg_hb0W5zTSsAeF40CGneJvbx8VP5L7b\/preview","Genero":" Animacao, Comedia","Idade":"Livre","Ano":"2020","Legenda":"0","foto":"16105041625ffe57e2682fa.png","fotogrande":"16105041625ffe57e26ee83.png","banner":"16105041625ffe57e25f1ab.png"},"193":{"ID":"189","Nome":"Star Wars - A Ascensao Skywalker","Link":"https:\/\/drive.google.com\/file\/d\/1L3XcWt4pWWISp-BoU1bScLjjqpdjHrRQ\/preview","Genero":"Ficcao cientifica, Acao","Idade":"12","Ano":"2019","Legenda":"0","foto":"1614698091603e566b4c716.png","fotogrande":"1614698091603e566b42226.png","banner":"1614698091603e566b361be.png"},"194":{"ID":"171","Nome":"Stuber","Link":"https:\/\/drive.google.com\/file\/d\/1LSsgWTx8MjNHn6BqlYf2M53fteE8TU2N\/preview","Genero":"Action, Aventura, Crime","Idade":"16","Ano":"2019","Legenda":"0","foto":"1613573351602d2ce7194cb.png","fotogrande":"1613573351602d2ce70ccb5.png","banner":"1613573350602d2ce6f28c2.png"},"195":{"ID":"63","Nome":"Sua Alteza","Link":"https:\/\/drive.google.com\/file\/d\/16zZaliyduXKzpgwBsES8vlMmEUc896nO\/preview","Genero":"Comedia, Aventura, Fantasia","Idade":"16","Ano":"2011","Legenda":"0","foto":"15926027305eed306a06904.png","fotogrande":"15926027305eed306a06904.png","banner":null},"196":{"ID":"7","Nome":"Superacao - O Milagre da Fe","Link":"https:\/\/drive.google.com\/file\/d\/1vRIuGPje5-AIJXaJJwXWW3HeNietYp1g\/preview","Genero":"Biografia, Drama, Gospel","Idade":"10","Ano":"2019","Legenda":"0","foto":"15869068175e9646c1c3094.png","fotogrande":"15869068175e9646c1c3094.png","banner":null},"197":{"ID":"172","Nome":"Ta Todo Mundo Louco","Link":"https:\/\/drive.google.com\/file\/d\/1ovadGmcIJ4JGRwTa4HF8-7rkvXnF-DK8\/preview","Genero":"Comedia, Aventura","Idade":"Livre","Ano":"2001","Legenda":"0","foto":"1613577641602d3da901415.png","fotogrande":"1613577640602d3da8e5c2d.png","banner":"1613577640602d3da8d6c1e.png"},"198":{"ID":"113","Nome":"Tempestade - Planeta em Furia","Link":"https:\/\/drive.google.com\/file\/d\/1TxeixZncR3ZCbvrstlDO87Wo7QWmWneQ\/preview","Genero":"Ficcao cientifica, Action","Idade":"12","Ano":"2017","Legenda":"1","foto":"16039361135f9a1f71f077b.png","fotogrande":"16039361135f9a1f71f077b.png","banner":null},"199":{"ID":"83","Nome":"Thor","Link":"https:\/\/drive.google.com\/file\/d\/1DPsDRevJ9z0tXHsnS2NE_Ra7Uv5lkB0Q\/preview","Genero":"Aventura, Fantasia, Action","Idade":"10","Ano":"2011","Legenda":"0","foto":"15966450515f2adebbc004d.png","fotogrande":"15966450515f2adebbc004d.png","banner":null},"200":{"ID":"202","Nome":"Tom & Jerry - O Filme","Link":"https:\/\/drive.google.com\/file\/d\/1p9uBeLxcwQwNTnM0C-4t5KD2Mfwd54-Z\/preview","Genero":"Action, Comedia, Familia, Animacao","Idade":"Livre","Ano":"2021","Legenda":"0","foto":"1617728977606c95d18bd00.png","fotogrande":"1617728977606c95d17f8d7.png","banner":"1617728977606c95d16f095.png"},"201":{"ID":"20","Nome":"Transformers","Link":"https:\/\/drive.google.com\/file\/d\/1oZikOs-25AiTpMa7rEPUsE_EfcHziX_w\/preview","Genero":"Aventura, Ficcao cientifica, Action","Idade":"10","Ano":"2007","Legenda":"0","foto":"15875174955e9f983715fdc.png","fotogrande":"15875174955e9f983715fdc.png","banner":null},"202":{"ID":"34","Nome":"Transformers: O Ultimo Cavaleiro","Link":"https:\/\/drive.google.com\/file\/d\/1VbEL19BWyh9CVYjgMepXQQblo18q6hdy\/preview","Genero":"Action, Ficcao cientifica, Thriller, Aventura","Idade":"12","Ano":"2017","Legenda":"0","foto":"15893441005ebb776407437.png","fotogrande":"15893441005ebb776407437.png","banner":null},"203":{"ID":"146","Nome":"Tres Homens em Conflito","Link":"https:\/\/drive.google.com\/file\/d\/1zHVlIEgNN20FBCAbsv9tuObKuXd8b2AB\/preview","Genero":"Faroeste","Idade":"14","Ano":"1966","Legenda":"0","foto":"16068272865fc63d16b7ce3.png","fotogrande":"16068272865fc63d16b7ce3.png","banner":"16068272865fc63d16b7ce3.png"},"204":{"ID":"147","Nome":"Um Amor para Recordar","Link":"https:\/\/drive.google.com\/file\/d\/13zeq62HnnIPAJUgoQBXH0MXqq-ZIOVXb\/preview","Genero":"Romance, Drama, Gospel","Idade":"Livre","Ano":"2002","Legenda":"0","foto":"16069598345fc842da3ff38.png","fotogrande":"16069598345fc842da3ff38.png","banner":"16069598345fc842da3ff38.png"},"205":{"ID":"145","Nome":"Um Caminho de Luz","Link":"https:\/\/drive.google.com\/file\/d\/1MXEreVII9r_nyZqoJcxY1p4CQCgNgN_S\/preview","Genero":"Drama, Gospel","Idade":"12","Ano":"2008","Legenda":"0","foto":"16067667585fc550a6229c7.png","fotogrande":"16067667585fc550a6229c7.png","banner":"16067667585fc550a6229c7.png"},"206":{"ID":"142","Nome":"Um Olhar do Paraiso","Link":"https:\/\/drive.google.com\/file\/d\/1MB7NGON37q1WKhDsqCayYVfh0_mW4mSW\/preview","Genero":"Drama, Misterio, Gospel","Idade":"14","Ano":"2009","Legenda":"0","foto":"16067658105fc54cf29332b.png","fotogrande":"16067658105fc54cf29332b.png","banner":"16067658105fc54cf29332b.png"},"207":{"ID":"192","Nome":"Um Principe em Nova York 2","Link":"https:\/\/drive.google.com\/file\/d\/1K2YuB-CQ778UZqDpme8hEhgLlX2a1M9P\/preview","Genero":"Comedia, Romance, Aventura","Idade":"14","Ano":"2021","Legenda":"0","foto":"1615426849604975218f4a1.png","fotogrande":"1615426849604975218638c.png","banner":"1615426849604975217d013.png"},"208":{"ID":"27","Nome":"Um Romance Cristao","Link":"https:\/\/drive.google.com\/file\/d\/1MM3EJlAQfDrvtjiqq9nzOg_XfA1ZAPUN\/preview","Genero":"Comedia , Romance, Gospel","Idade":"14","Ano":"2014","Legenda":"0","foto":"15883079935eaba819d2beb.png","fotogrande":"15883079935eaba819d2beb.png","banner":null},"209":{"ID":"143","Nome":"Um Sonho de Liberdade","Link":"https:\/\/drive.google.com\/file\/d\/18aEW_62XLkwDZrhJ8Pw-WKwyKZcNAF46\/preview","Genero":"Drama, Ficcao policial","Idade":"16","Ano":"1994","Legenda":"0","foto":"16067662975fc54ed9bf664.png","fotogrande":"16067662975fc54ed9bf664.png","banner":"16067662975fc54ed9bf664.png"},"210":{"ID":"144","Nome":"Um Sonho Possivel","Link":"https:\/\/drive.google.com\/file\/d\/1CebBgpdoOM2GZlsukBr7NqhwottXuVci\/preview","Genero":"Esporte, Drama","Idade":"10","Ano":"2009","Legenda":"0","foto":"16067665625fc54fe24d476.png","fotogrande":"16067665625fc54fe24d476.png","banner":"16067665625fc54fe24d476.png"},"211":{"ID":"26","Nome":"Uma Batalha De Fe","Link":"https:\/\/drive.google.com\/file\/d\/1xrj51_QN3bf-2TRgnKppnDRocvnO71Qy\/preview","Genero":"Familia, Gospel","Idade":"10","Ano":"2019","Legenda":"0","foto":"15883001275eab895f10a84.png","fotogrande":"15883001275eab895f10a84.png","banner":null},"212":{"ID":"33","Nome":"Uma Noiva em Apuros","Link":"https:\/\/drive.google.com\/file\/d\/19ixIv_IF7LGP7rgyLd1bXXeriExwsmV-\/preview","Genero":"Romance, Comedia","Idade":"10","Ano":"2018","Legenda":"0","foto":"15893297585ebb3f5e7c07f.png","fotogrande":"15893297585ebb3f5e7c07f.png","banner":null},"213":{"ID":"122","Nome":"Ursos Sem Curso","Link":"https:\/\/drive.google.com\/file\/d\/1d46F_AQXGYXLv7iCDtFjxN7y6nU-jKd8\/preview","Genero":"Fam\u00c3\u00adlia, Animacao, Aventura, Comedia","Idade":"Livre","Ano":"2020","Legenda":"0","foto":"16054728215fb1923529ce9.png","fotogrande":"16054728215fb1923529ce9.png","banner":null},"214":{"ID":"12","Nome":"Velozes E Furiosos 8","Link":"https:\/\/drive.google.com\/file\/d\/1g6ERMINu04G5bxp5sX_4DZb82k0wLp1w\/preview","Genero":"Action, Crime, Thriller","Idade":"14","Ano":"2017","Legenda":"0","foto":"15869310245e96a55097d82.png","fotogrande":"15869310245e96a55097d82.png","banner":null},"215":{"ID":"219","Nome":"Velozes e Furiosos 9","Link":"https:\/\/drive.google.com\/file\/d\/1zI62LU4NzjOmhJJOrtZ7OhvT9M0zD92Q\/preview","Genero":"Action, Aventura","Idade":"14","Ano":"2021","Legenda":"0","foto":"16288084786115a51e8ddcb.png","fotogrande":"16288084786115a51e89d0a.png","banner":"16288084786115a51e846c1.png"},"216":{"ID":"54","Nome":"Vingadores - Guerra Infinita","Link":"https:\/\/drive.google.com\/file\/d\/1lOcR6TZKj5UlJ0sN4v3osfwj7g2DUIMT\/preview","Genero":"Aventura, Action, Ficcao Cientifica","Idade":"12","Ano":"2018","Legenda":"0","foto":"15921690855ee6927dcf828.png","fotogrande":"15921690855ee6927dcf828.png","banner":null},"217":{"ID":"60","Nome":"Vingadores - Ultimato","Link":"https:\/\/drive.google.com\/file\/d\/1NsrhURPox8AySQTt2eyznBJpBPON3I0n\/preview","Genero":"Aventura, Ficcao cientifica, Action","Idade":"12","Ano":"2019","Legenda":"0","foto":"15923522345ee95deaf0065.png","fotogrande":"15923522345ee95deaf0065.png","banner":null},"218":{"ID":"13","Nome":"Vingadores: Era De Ultron","Link":"https:\/\/drive.google.com\/file\/d\/1kSzLxqPrXB0BvmEa-6IsgXA9tak37JnF\/preview","Genero":"Action, Aventura, Ficcao Cientifica","Idade":"12","Ano":"2015","Legenda":"0","foto":"15874072085e9de968342ac.png","fotogrande":"15874072085e9de968342ac.png","banner":null},"219":{"ID":"220","Nome":"Viuva Negra","Link":"https:\/\/drive.google.com\/file\/d\/1IuBHe-F6NpJdfN5BW5gFDSQUO4YZZMpQ\/preview","Genero":"Action, Aventura","Idade":"12","Ano":"2021","Legenda":"0","foto":"16288089916115a71fdffb8.png","fotogrande":"16288089916115a71fda0b0.png","banner":"16288089916115a71fd358c.png"},"220":{"ID":"169","Nome":"Viva - A vida e uma Festa","Link":"https:\/\/drive.google.com\/file\/d\/1-xOkCl2ZQnkaaQVcisW2UhdRdm0L5TYc\/preview","Genero":"Infantil, Aventura, Animacao","Idade":"Livre","Ano":"2017","Legenda":"0","foto":"1613522231602c653788ff5.png","fotogrande":"1613522231602c65377bd66.png","banner":"1613522231602c65376fe6d.png"},"221":{"ID":"224","Nome":"Vixen - O Filme","Link":"https:\/\/drive.google.com\/file\/d\/1OVoZr_xmtVx1AQe8QxrQXKO6K6izq9x2\/preview","Genero":"Animacao, Action, Fantasia","Idade":"Livre","Ano":"2017","Legenda":"0","foto":"16310541886137e96c47ae9.png","fotogrande":"16310541886137e96c40cd5.png","banner":"16310541886137e96c36b87.png"},"222":{"ID":"183","Nome":"X-Men Apocalipse","Link":"https:\/\/drive.google.com\/file\/d\/1LKYbc1_0mvhIAcSXbbVlF3ULzRusULNk\/preview","Genero":"Action, Ficcao cientifica","Idade":"12","Ano":"2016","Legenda":"0","foto":"1614043583603459bf1184f.png","fotogrande":"1614043582603459bee02d5.png","banner":"1614043582603459bebee98.png"},"223":{"ID":"153","Nome":"Zohan - Um Agente Bom de Corte","Link":"https:\/\/drive.google.com\/file\/d\/1-VhHrezeCeW5c9wPhJU6S4irx-PEECi5\/preview","Genero":"Comedia, Action","Idade":"14","Ano":"2008","Legenda":"0","foto":"161110704360078ae3ae956.png","fotogrande":"161110704360078ae3a2805.png","banner":"161110704360078ae391b84.png"},"224":{"ID":"6","Nome":"Zumbilandia: Atire Duas Vezes","Link":"https:\/\/drive.google.com\/file\/d\/1O3Y4fxWsZzfv2Cg1mloyGzEZ4v_8ZWiI\/preview","Genero":"Action, Comedia, Terror","Idade":"16","Ano":"2019","Legenda":"0","foto":"15869067495e96467de996f.png","fotogrande":"15869067495e96467de996f.png","banner":null}}